apitools/__init__.py
apitools/clients/__init__.py
apitools/clients/dataflow/__init__.py
apitools/clients/dataflow/dataflow_v1b3_client.py
apitools/clients/dataflow/dataflow_v1b3_messages.py
google_apitools_dataflow_v1b3-0.5.16.20171003.dist-info/DESCRIPTION.rst
google_apitools_dataflow_v1b3-0.5.16.20171003.dist-info/METADATA
google_apitools_dataflow_v1b3-0.5.16.20171003.dist-info/RECORD
google_apitools_dataflow_v1b3-0.5.16.20171003.dist-info/WHEEL
google_apitools_dataflow_v1b3-0.5.16.20171003.dist-info/metadata.json
google_apitools_dataflow_v1b3-0.5.16.20171003.dist-info/top_level.txt
