Metadata-Version: 2.0
Name: google-apitools-dataflow-v1b3
Version: 0.5.16.20171003
Summary: Autogenerated apitools library for dataflow
Home-page: https://github.com/google/apitools
Author: Craig Citro
Author-email: craigcitro@google.com
License: Apache 2.0
Keywords: apitools apitools-dataflow dataflow
Platform: UNKNOWN
Classifier: Programming Language :: Python :: 2.7
Classifier: License :: OSI Approved :: Apache Software License
Requires-Dist: google-apitools (>=0.5.16,~=0.5)
Requires-Dist: httplib2 (>=0.9)
Requires-Dist: oauth2client (>=1.4.12)
